htmldump/__init__.py
htmldump/command.py
htmldump/html_parser.py
htmldump/html_utils.py
htmldump-0.2039.0.dist-info/LICENSE
htmldump-0.2039.0.dist-info/METADATA
htmldump-0.2039.0.dist-info/WHEEL
htmldump-0.2039.0.dist-info/entry_points.txt
htmldump-0.2039.0.dist-info/top_level.txt
htmldump-0.2039.0.dist-info/RECORD
