Metadata-Version: 2.1
Name: htmldump
Version: 0.2039.0
Summary: HTML Dumper
Home-page: https://sourceforge.net/p/htmldump/code/ci/stable/tree
Author: Louis RIVIERE
Author-email: louis@riviere.xyz
License: MIT
Keywords: utility
Platform: UNKNOWN
Classifier: Development Status :: 4 - Beta
Classifier: Intended Audience :: Developers
Classifier: Topic :: Software Development :: Testing
Classifier: License :: OSI Approved :: MIT License
Classifier: Programming Language :: Python :: 3
